EyeLinkCoreGraphicsOpensesame/.git/COMMIT_EDITMSG
EyeLinkCoreGraphicsOpensesame/.git/FETCH_HEAD
EyeLinkCoreGraphicsOpensesame/.git/HEAD
EyeLinkCoreGraphicsOpensesame/.git/config
EyeLinkCoreGraphicsOpensesame/.git/description
EyeLinkCoreGraphicsOpensesame/.git/hooks/applypatch-msg.sample
EyeLinkCoreGraphicsOpensesame/.git/hooks/commit-msg.sample
EyeLinkCoreGraphicsOpensesame/.git/hooks/fsmonitor-watchman.sample
EyeLinkCoreGraphicsOpensesame/.git/hooks/post-update.sample
EyeLinkCoreGraphicsOpensesame/.git/hooks/pre-applypatch.sample
EyeLinkCoreGraphicsOpensesame/.git/hooks/pre-commit.sample
EyeLinkCoreGraphicsOpensesame/.git/hooks/pre-merge-commit.sample
EyeLinkCoreGraphicsOpensesame/.git/hooks/pre-push.sample
EyeLinkCoreGraphicsOpensesame/.git/hooks/pre-rebase.sample
EyeLinkCoreGraphicsOpensesame/.git/hooks/pre-receive.sample
EyeLinkCoreGraphicsOpensesame/.git/hooks/prepare-commit-msg.sample
EyeLinkCoreGraphicsOpensesame/.git/hooks/push-to-checkout.sample
EyeLinkCoreGraphicsOpensesame/.git/hooks/sendemail-validate.sample
EyeLinkCoreGraphicsOpensesame/.git/hooks/update.sample
EyeLinkCoreGraphicsOpensesame/.git/index
EyeLinkCoreGraphicsOpensesame/.git/info/exclude
EyeLinkCoreGraphicsOpensesame/.git/logs/HEAD
EyeLinkCoreGraphicsOpensesame/.git/logs/refs/heads/main
EyeLinkCoreGraphicsOpensesame/.git/objects/06/606e3c96fd10ebefdb4791525fb5c601b190ba
EyeLinkCoreGraphicsOpensesame/.git/objects/08/3e6dde0a140649e4d4307306b599d7497936bd
EyeLinkCoreGraphicsOpensesame/.git/objects/0b/7ca6c61e1d91d83304d8a0f1859746074364b9
EyeLinkCoreGraphicsOpensesame/.git/objects/14/befc4e60edd40c306e84a9d67a28c82fe5448c
EyeLinkCoreGraphicsOpensesame/.git/objects/1b/391ff6b7da5673c947ed8c1ea7c206862effe5
EyeLinkCoreGraphicsOpensesame/.git/objects/1e/bf1daecb36e802c82f7d69c51cb8f86a30536e
EyeLinkCoreGraphicsOpensesame/.git/objects/84/5c367c0e6bf05b60f4a5d714522eeac810b3e0
EyeLinkCoreGraphicsOpensesame/.git/objects/ac/913fec5600b82cabbd389958d0385047000686
opensesame_eyelink_coregraphics-2.1.1197.0.dist-info/LICENSE
opensesame_eyelink_coregraphics-2.1.1197.0.dist-info/METADATA
opensesame_eyelink_coregraphics-2.1.1197.0.dist-info/WHEEL
opensesame_eyelink_coregraphics-2.1.1197.0.dist-info/RECORD
